{
  "$schema": "https://schema.management.azure.com/schemas/2019-04-01/deploymentTemplate.json#",
  "contentVersion": "1.0.0.0",
  "resources": [
    {
      "type": "Microsoft.Network/publicIPAddresses",
      "apiVersion": "2019-04-01",
      "name": "WinVMPublicIP",
      "location": "eastus",
      "properties": {
        "publicIPAllocationMethod": "Dynamic"
      }
    },
    {
      "type": "Microsoft.Network/networkSecurityGroups",
      "apiVersion": "2019-04-01",
      "name": "WinVMNSG",
      "location": "eastus",
      "properties": {
        "securityRules": [
          {
            "name": "AllowRDP",
            "properties": {
              "protocol": "Tcp",
              "sourcePortRange": "*",
              "destinationPortRange": "3389",
              "sourceAddressPrefix": "*",
              "destinationAddressPrefix": "*",
              "access": "Allow",
              "priority": 100,
              "direction": "Inbound"
            }
          }
        ]
      }
    },
    {
      "type": "Microsoft.Network/networkInterfaces",
      "apiVersion": "2019-04-01",
      "name": "WinVMNic",
      "location": "eastus",
      "dependsOn": [
        "WinVMNSG"
      ],
      "properties": {
        "ipConfigurations": [
          {
            "name": "ipconfig",
            "properties": {
              "privateIPAllocationMethod": "Dynamic",
              "publicIPAddress": {
                "id": "[resourceId('Microsoft.Network/publicIPAddresses', 'WinVMPublicIP')]"
              },
              "subnet": {
                "id": "[variables('subnetRef')]"
              }
            }
          }
        ]
      }
    },
    {
      "type": "Microsoft.Compute/virtualMachines",
      "apiVersion": "2019-07-01",
      "name": "WinVM",
      "location": "eastus",
      "dependsOn": [
        "WinVMNic"
      ],
      "properties": {
        "hardwareProfile": {
          "vmSize": "Standard_DS1_v2"
        },
        "osProfile": {
          "computerName": "WinVM",
          "adminUsername": "VM",
          "adminPassword": "VM@123456789"
        },
        "storageProfile": {
          "imageReference": {
            "publisher": "MicrosoftWindowsServer",
            "offer": "WindowsServer",
            "sku": "2019-Datacenter",
            "version": "latest"
          },
          "osDisk": {
            "name": "WinVMDisk",
            "createOption": "FromImage"
          }
        },
        "networkProfile": {
          "networkInterfaces": [
            {
              "id": "[resourceId('Microsoft.Network/networkInterfaces', 'WinVMNic')]"
            }
          ]
        }
      }
    },
    {
      "type": "Microsoft.Network/publicIPAddresses",
      "apiVersion": "2019-04-01",
      "name": "LXVMPublicIP",
      "location": "eastus",
      "properties": {
        "publicIPAllocationMethod": "Dynamic"
      }
    },
    {
      "type": "Microsoft.Network/networkSecurityGroups",
      "apiVersion": "2019-04-01",
      "name": "LXVMNSG",
      "location": "eastus",
      "properties": {
        "securityRules": [
          {
            "name": "AllowSSH",
            "properties": {
              "protocol": "Tcp",
              "sourcePortRange": "*",
              "destinationPortRange": "22",
              "sourceAddressPrefix": "*",
              "destinationAddressPrefix": "*",
              "access": "Allow",
              "priority": 100,
              "direction": "Inbound"
            }
          }
        ]
      }
    },
    {
      "type": "Microsoft.Network/networkInterfaces",
      "apiVersion": "2019-04-01",
      "name": "LXVMNic",
      "location": "eastus",
      "dependsOn": [
        "LXVMNSG"
      ],
      "properties": {
        "ipConfigurations": [
          {
            "name": "ipconfig",
            "properties": {
              "privateIPAllocationMethod": "Dynamic",
              "publicIPAddress": {
                "id": "[resourceId('Microsoft.Network/publicIPAddresses', 'LXVMPublicIP')]"
              },
              "subnet": {
                "id": "[variables('subnetRef')]"
              }
            }
          }
        ]
      }
    },
    {
      "type": "Microsoft.Compute/virtualMachines",
      "apiVersion": "2019-07-01",
      "name": "LXVM",
      "location": "eastus",
      "dependsOn": [
        "LXVMNic"
      ],
      "properties": {
        "hardwareProfile": {
          "vmSize": "Standard_DS1_v2"
        },
        "osProfile": {
          "computerName": "LXVM",
          "adminUsername": "VM",
          "adminPassword": "VM@123456789"
        },
        "storageProfile": {
          "imageReference": {
            "publisher": "Canonical",
            "offer": "UbuntuServer",
            "sku": "18.04-LTS",
            "version": "latest"
          },
          "osDisk": {
            "name": "LXVMDisk",
            "createOption": "FromImage"
          }
        },
        "networkProfile": {
          "networkInterfaces": [
            {
              "id": "[resourceId('Microsoft.Network/networkInterfaces', 'LXVMNic')]"
            }
          ]
        }
      }
    }
  ],
  "variables": {
    "subnetRef": "[resourceId('Microsoft.Network/virtualNetworks/subnets', 'Vnet-peering', 'Subnet-1')]"
  }
}
